README.md
setup.py
py3do/__init__.py
py3do.egg-info/PKG-INFO
py3do.egg-info/SOURCES.txt
py3do.egg-info/dependency_links.txt
py3do.egg-info/requires.txt
py3do.egg-info/top_level.txt