Metadata-Version: 1.2
Name: py3do
Version: 0.0.1
Summary: py3do - Construct models for 3d printing in Python
Home-page: https://github.com/jszymon/py3do
Author: Szymon Jaroszewicz
Author-email: jszymon@gmail.com
License: GNU General Public License V.3 or later
Platform: UNKNOWN
Requires-Python: >=3.5
